relace/__init__.py
relace/_base_client.py
relace/_client.py
relace/_compat.py
relace/_constants.py
relace/_exceptions.py
relace/_files.py
relace/_git.py
relace/_models.py
relace/_qs.py
relace/_resource.py
relace/_response.py
relace/_streaming.py
relace/_types.py
relace/_version.py
relace/py.typed
relace/_utils/__init__.py
relace/_utils/_compat.py
relace/_utils/_datetime_parse.py
relace/_utils/_logs.py
relace/_utils/_proxy.py
relace/_utils/_reflection.py
relace/_utils/_resources_proxy.py
relace/_utils/_streams.py
relace/_utils/_sync.py
relace/_utils/_transform.py
relace/_utils/_typing.py
relace/_utils/_utils.py
relace/lib/.keep
relace/resources/__init__.py
relace/resources/repo_token.py
relace/resources/repo/__init__.py
relace/resources/repo/file.py
relace/resources/repo/repo.py
relace/types/__init__.py
relace/types/file.py
relace/types/file_param.py
relace/types/repo_clone_params.py
relace/types/repo_clone_response.py
relace/types/repo_create_params.py
relace/types/repo_info.py
relace/types/repo_list_params.py
relace/types/repo_list_response.py
relace/types/repo_metadata.py
relace/types/repo_retrieve_params.py
relace/types/repo_retrieve_response.py
relace/types/repo_token_create_params.py
relace/types/repo_token_create_response.py
relace/types/repo_token_get_response.py
relace/types/repo_update_params.py
relace/types/repo/__init__.py
relace/types/repo/file_upload_params.py
relace-1.0.4.dist-info/METADATA
relace-1.0.4.dist-info/WHEEL
relace-1.0.4.dist-info/licenses/LICENSE
relace-1.0.4.dist-info/RECORD
